pypscan/__init__.py
pypscan/pypscan.ipynb
pypscan/pypscan.py
pypscan/utils.py
pypscan/demo/create_data.ipynb
pypscan/demo/param0_a/param1_0/file.png
pypscan/demo/param0_a/param1_1/file.png
pypscan/demo/param0_a/param1_2/file.png
pypscan/demo/param0_b/param1_0/file.png
pypscan/demo/param0_b/param1_1/file.png
pypscan/demo/param0_b/param1_2/file.png
pypscan/demo/param0_c/param1_0/file.png
pypscan/demo/param0_c/param1_2/file.png
pypscan-2025.0.1.dist-info/METADATA
pypscan-2025.0.1.dist-info/WHEEL
pypscan-2025.0.1.dist-info/RECORD
