Metadata-Version: 2.4
Name: pypscan
Version: 2025.0.1
Summary: Parametric file browser written in pure python.
Project-URL: Homepage, https://github.com/nollde/pypscan
Project-URL: Issues, https://github.com/nollde/pypscan/issues
Author-email: Dennis Noll <github@nollde.de>
License: MIT License
Keywords: filebrowser,python
Classifier: Development Status :: 4 - Beta
Classifier: License :: OSI Approved :: MIT License
Classifier: Programming Language :: Python :: 3
Requires-Python: >=3.8
Requires-Dist: ipywidgets
Requires-Dist: numpy
Requires-Dist: pillow
Requires-Dist: tqdm
Requires-Dist: wand
